[
  {
    "value": "Sharp",
    "count": 211
  },
  {
    "value": "I See Dead People",
    "count": 208
  },
  {
    "value": "Lightning",
    "count": 160
  },
  {
    "value": "Ancient History",
    "count": 144
  },
  {
    "value": "Imprisoned",
    "count": 144
  },
  {
    "value": "Naked",
    "count": 134
  },
  {
    "value": "Till Death Do Us Part",
    "count": 133
  },
  {
    "value": "Around The World",
    "count": 132
  },
  {
    "value": "Grieving Widow",
    "count": 131
  },
  {
    "value": "Hugin And Munin",
    "count": 131
  },
  {
    "value": "Life Through A Broken Lense",
    "count": 131
  },
  {
    "value": "The Creeper",
    "count": 129
  },
  {
    "value": "Piercing",
    "count": 127
  },
  {
    "value": "Leave Me Alone",
    "count": 126
  },
  {
    "value": "Life Is Hell",
    "count": 126
  },
  {
    "value": "Escaping Darkness",
    "count": 124
  },
  {
    "value": "Unseen Death",
    "count": 124
  },
  {
    "value": "Moonshot",
    "count": 123
  },
  {
    "value": "The Fly",
    "count": 123
  },
  {
    "value": "Times up",
    "count": 123
  },
  {
    "value": "The High Life",
    "count": 117
  },
  {
    "value": "Trapped",
    "count": 116
  },
  {
    "value": "Lost Childhood",
    "count": 112
  },
  {
    "value": "Explorer",
    "count": 111
  },
  {
    "value": "I Made A Mistake",
    "count": 111
  },
  {
    "value": "Facing Death",
    "count": 107
  },
  {
    "value": "Soldiers Pain",
    "count": 105
  },
  {
    "value": "Unimaginable",
    "count": 102
  },
  {
    "value": "Popeye",
    "count": 97
  },
  {
    "value": "Crypt Coin",
    "count": 90
  },
  {
    "value": "None",
    "count": 68
  },
  {
    "value": "Neon",
    "count": 64
  },
  {
    "value": "Double Snake",
    "count": 61
  },
  {
    "value": "Fantasy Glow",
    "count": 60
  },
  {
    "value": "Smokey",
    "count": 58
  },
  {
    "value": "Spider",
    "count": 49
  },
  {
    "value": "Vinyl",
    "count": 49
  },
  {
    "value": "Robotic",
    "count": 48
  },
  {
    "value": "Snake",
    "count": 38
  },
  {
    "value": "Self Reflection",
    "count": 30
  },
  {
    "value": "Neon Skull And Cross",
    "count": 26
  },
  {
    "value": "In Lucifer We Trust",
    "count": 25
  },
  {
    "value": "Love Eyes",
    "count": 24
  },
  {
    "value": "Half Moon",
    "count": 23
  },
  {
    "value": "Silver",
    "count": 21
  },
  {
    "value": "Dystopia",
    "count": 20
  },
  {
    "value": "Cats Eyes",
    "count": 19
  },
  {
    "value": "Kheper",
    "count": 19
  },
  {
    "value": "Honey",
    "count": 18
  },
  {
    "value": "Canary Diamond",
    "count": 17
  },
  {
    "value": "Heavens Gateway",
    "count": 17
  },
  {
    "value": "Machine Gun Eye",
    "count": 17
  },
  {
    "value": "Ruby",
    "count": 17
  },
  {
    "value": "Specs",
    "count": 17
  },
  {
    "value": "Temporal Rift",
    "count": 17
  },
  {
    "value": "Eye Patch",
    "count": 16
  },
  {
    "value": "Gold",
    "count": 16
  },
  {
    "value": "Pink Sapphire",
    "count": 16
  },
  {
    "value": "Endless Void",
    "count": 15
  },
  {
    "value": "Hells Gateway",
    "count": 15
  },
  {
    "value": "Lizards Eye",
    "count": 15
  },
  {
    "value": "Oh Beehave",
    "count": 15
  },
  {
    "value": "Soul Cry",
    "count": 15
  },
  {
    "value": "Devilish Sight",
    "count": 14
  },
  {
    "value": "Mad Scientist",
    "count": 14
  },
  {
    "value": "Magic Mushroom",
    "count": 14
  },
  {
    "value": "Shady",
    "count": 14
  },
  {
    "value": "Time Reversed",
    "count": 14
  },
  {
    "value": "Topaz",
    "count": 14
  },
  {
    "value": "Contagion",
    "count": 13
  },
  {
    "value": "Deadeye",
    "count": 13
  },
  {
    "value": "Emerald",
    "count": 13
  },
  {
    "value": "Lavendar Quartz",
    "count": 13
  },
  {
    "value": "Skulls",
    "count": 13
  },
  {
    "value": "Time Warp",
    "count": 13
  },
  {
    "value": "Brown Jasper",
    "count": 12
  },
  {
    "value": "Side Skulls",
    "count": 12
  },
  {
    "value": "Eyes",
    "count": 11
  },
  {
    "value": "Revolver",
    "count": 11
  },
  {
    "value": "Death Stare",
    "count": 10
  },
  {
    "value": "Dragons",
    "count": 10
  },
  {
    "value": "Faiths Guardian",
    "count": 10
  },
  {
    "value": "One Eye",
    "count": 9
  },
  {
    "value": "Eye See All",
    "count": 8
  },
  {
    "value": "Four Twenty",
    "count": 8
  },
  {
    "value": "Light Up My Life",
    "count": 8
  },
  {
    "value": "The Dons M-Frames",
    "count": 8
  },
  {
    "value": "Weed",
    "count": 8
  },
  {
    "value": "Wow",
    "count": 7
  },
  {
    "value": "See No Evil",
    "count": 6
  },
  {
    "value": "Looking Into The Future",
    "count": 5
  },
  {
    "value": "Jarvis",
    "count": 4
  },
  {
    "value": "Knife Eye",
    "count": 4
  },
  {
    "value": "Flame Eyes",
    "count": 3
  },
  {
    "value": "VR",
    "count": 2
  },
  {
    "value": "Blazin",
    "count": 1
  }
]